makem4b/__init__.py
makem4b/__main__.py
makem4b/analysis.py
makem4b/base.py
makem4b/cli/__init__.py
makem4b/cli/base.py
makem4b/cli/decorators.py
makem4b/cli/env.py
makem4b/cli/options.py
makem4b/commands/__init__.py
makem4b/commands/merge.py
makem4b/commands/recursive.py
makem4b/constants.py
makem4b/emoji.py
makem4b/exceptions.py
makem4b/ffmpeg.py
makem4b/intermediates.py
makem4b/metadata.py
makem4b/models.py
makem4b/types.py
makem4b/utils.py
makem4b-1.3.0.dist-info/METADATA
makem4b-1.3.0.dist-info/WHEEL
makem4b-1.3.0.dist-info/entry_points.txt
makem4b-1.3.0.dist-info/RECORD
