Metadata-Version: 2.1
Name: makem4b
Version: 1.3.0
Summary: Merge audio files into an audiobook.
Home-page: https://github.com/janw/makem4b
License: Apache-2.0
Author: Jan Willhaus
Author-email: mail@janwillhaus.de
Requires-Python: >=3.12,<4.0
Classifier: Development Status :: 4 - Beta
Classifier: Environment :: Console
Classifier: Intended Audience :: Information Technology
Classifier: License :: OSI Approved :: Apache Software License
Classifier: Operating System :: MacOS
Classifier: Operating System :: Microsoft :: Windows
Classifier: Operating System :: POSIX :: Linux
Classifier: Programming Language :: Python :: 3
Classifier: Programming Language :: Python :: 3.12
Classifier: Programming Language :: Python :: 3.13
Classifier: Topic :: Multimedia
Classifier: Topic :: Multimedia :: Sound/Audio
Classifier: Topic :: Utilities
Requires-Dist: loguru (>=0.7.2,<0.8.0)
Requires-Dist: pydantic (>=2.10.1,<3.0.0)
Requires-Dist: rich-click (>=1.8.4,<2.0.0)
Project-URL: Bug Reports, https://github.com/janw/makem4b/issues
Project-URL: Repository, https://github.com/janw/makem4b
